bestnewmusic/__init__.py
bestnewmusic/__main__.py
bestnewmusic/sources.py
bestnewmusic/util.py
bestnewmusic-0.5.9.dist-info/LICENSE
bestnewmusic-0.5.9.dist-info/METADATA
bestnewmusic-0.5.9.dist-info/WHEEL
bestnewmusic-0.5.9.dist-info/entry_points.txt
bestnewmusic-0.5.9.dist-info/top_level.txt
bestnewmusic-0.5.9.dist-info/RECORD
