Metadata-Version: 2.1
Name: bestnewmusic
Version: 0.5.9
Summary: View music reviews and weekly radio charts in the terminal
Home-page: https://github.com/ddbourgin/bestnewmusic
Author: David Bourgin
Author-email: ddbourgin@gmail.com
License: MIT
Project-URL: Source, https://github.com/ddbourgin/bestnewmusic
Keywords: music,terminal
Classifier: Development Status :: 3 - Alpha
Classifier: License :: OSI Approved :: MIT License
Classifier: Environment :: Console
Classifier: Programming Language :: Python :: 3
License-File: LICENSE
Requires-Dist: beautifulsoup4 (>=4.8.2)
Requires-Dist: html5lib (>=1.0.1)
Requires-Dist: requests (>=2.23.0)
Requires-Dist: termcolor (>=1.1.0)
Requires-Dist: fake-useragent
Requires-Dist: selenium (>=3.141.0)
Requires-Dist: webdriver-manager (>=3.5.2)
